bmds_ui/__init__.py
bmds_ui/__main__.py
bmds_ui/gitcommit.json
bmds_ui/webpack-stats.json
bmds_ui/analysis/__init__.py
bmds_ui/analysis/admin.py
bmds_ui/analysis/api.py
bmds_ui/analysis/apps.py
bmds_ui/analysis/constants.py
bmds_ui/analysis/executor.py
bmds_ui/analysis/forms.py
bmds_ui/analysis/models.py
bmds_ui/analysis/schema.py
bmds_ui/analysis/serializers.py
bmds_ui/analysis/signals.py
bmds_ui/analysis/tasks.py
bmds_ui/analysis/transforms.py
bmds_ui/analysis/utils.py
bmds_ui/analysis/views.py
bmds_ui/analysis/fixtures/initial_data.json
bmds_ui/analysis/migrations/0001_initial.py
bmds_ui/analysis/migrations/0002_fixtures.py
bmds_ui/analysis/migrations/0003_reversions.py
bmds_ui/analysis/migrations/0004_collection_analysis_last_updated_analysis_starred_and_more.py
bmds_ui/analysis/migrations/0005_collection_bg_color.py
bmds_ui/analysis/migrations/0006_alter_collection_options.py
bmds_ui/analysis/migrations/__init__.py
bmds_ui/analysis/reporting/__init__.py
bmds_ui/analysis/reporting/analytics.py
bmds_ui/analysis/reporting/cache.py
bmds_ui/analysis/reporting/docx.py
bmds_ui/analysis/reporting/excel.py
bmds_ui/analysis/templates/analysis/_errors.html
bmds_ui/analysis/templates/analysis/analysis_confirm_delete.html
bmds_ui/analysis/templates/analysis/analysis_detail.html
bmds_ui/analysis/templates/analysis/analysis_history.html
bmds_ui/analysis/templates/analysis/analytics.html
bmds_ui/analysis/templates/analysis/desktop_home.html
bmds_ui/analysis/templates/analysis/home.html
bmds_ui/analysis/templates/analysis/polyk.html
bmds_ui/analysis/templates/analysis/rao-scott.html
bmds_ui/analysis/templates/analysis/fragments/collection_form.html
bmds_ui/analysis/templates/analysis/fragments/collection_li.html
bmds_ui/analysis/templates/analysis/fragments/td_star.html
bmds_ui/analysis/validators/__init__.py
bmds_ui/analysis/validators/datasets.py
bmds_ui/analysis/validators/models.py
bmds_ui/analysis/validators/options.py
bmds_ui/analysis/validators/selectors.py
bmds_ui-25.1.dist-info/entry_points.txt
bmds_ui-25.1.dist-info/licenses/LICENSE
bmds_ui-25.1.dist-info/WHEEL
bmds_ui-25.1.dist-info/METADATA
bmds_ui-25.1.dist-info/RECORD
