Metadata-Version: 2.4
Name: bmds_ui
Version: 25.1
Summary: U.S. EPA Dose Response Modeling Software User Interface
Keywords: dose response,toxicology,risk assessment
Author: BMDS Development Team
Author-email: Andy Shapiro <shapiro.andy@epa.gov>
Requires-Python: >=3.11
Classifier: Intended Audience :: Science/Research
Classifier: License :: OSI Approved :: MIT License
Classifier: Programming Language :: Python :: 3.11
Classifier: Programming Language :: Python :: 3.12
Classifier: Programming Language :: Python :: 3.13
Classifier: Topic :: Scientific/Engineering
License-File: LICENSE
Requires-Dist: pybmds==25.1
Requires-Dist: Django~=5.1.2
Requires-Dist: django-anymail~=12.0
Requires-Dist: django-redis~=5.4.0
Requires-Dist: django-webpack-loader~=3.1.1
Requires-Dist: djangorestframework~=3.15.2
Requires-Dist: uritemplate~=4.1.1
Requires-Dist: django-reversion~=5.1.0
Requires-Dist: PyYAML~=6.0.2
Requires-Dist: celery~=5.4.0
Requires-Dist: billiard~=4.2.1
Requires-Dist: kombu~=5.4.2
Requires-Dist: plotly~=6.0.0
Requires-Dist: redis~=5.2.1
Requires-Dist: packaging~=24.2
Requires-Dist: textual==2.1.2
Requires-Dist: whitenoise~=6.9.0
Requires-Dist: flit~=3.11.0 ; extra == "dev"
Requires-Dist: poethepoet~=0.33.0 ; extra == "dev"
Requires-Dist: django-debug-toolbar~=5.0.1 ; extra == "dev"
Requires-Dist: django_extensions~=3.2.3 ; extra == "dev"
Requires-Dist: django-browser-reload~=1.18.0 ; extra == "dev"
Requires-Dist: pytest~=8.3.3 ; extra == "dev"
Requires-Dist: pytest-django~=4.10.0 ; extra == "dev"
Requires-Dist: vcrpy~=7.0.0 ; extra == "dev"
Requires-Dist: pytest-recording~=0.13.2 ; extra == "dev"
Requires-Dist: pytest-asyncio~=0.25.3 ; extra == "dev"
Requires-Dist: coverage~=7.6.4 ; extra == "dev"
Requires-Dist: playwright~=1.50.0 ; extra == "dev"
Requires-Dist: pytest-playwright~=0.7.0 ; extra == "dev"
Requires-Dist: ruff~=0.9.10 ; extra == "dev"
Requires-Dist: psycopg2-binary~=2.9.10 ; extra == "pg"
Requires-Dist: gunicorn~=23.0.0 ; extra == "prod"
Requires-Dist: sentry-sdk~=2.22.0 ; extra == "prod"
Project-URL: Changes, https://github.com/USEPA/bmds-ui/blob/main/HISTORY.md
Project-URL: Download, https://pypi.org/project/bmds-ui/
Project-URL: Issue Tracker, https://github.com/USEPA/bmds-ui/issues
Project-URL: Source, https://github.com/USEPA/bmds-ui
Provides-Extra: dev
Provides-Extra: pg
Provides-Extra: prod
